Metadata-Version: 1.1
Name: python-ari
Version: 0.0.1
Summary: Python binding for ARI
Home-page: https://github.com/kickstandproject/python-ari
Author: Paul Belanger
Author-email: paul.belanger@polybeacon.com
License: Apache-2
Platform: UNKNOWN
Classifier: Development Status :: 3 - Alpha
Classifier: Environment :: Web Environment
Classifier: Intended Audience :: Developers
Classifier: Intended Audience :: Information Technology
Classifier: License :: OSI Approved :: Apache Software License
Classifier: Operating System :: OS Independent
Classifier: Programming Language :: Python
